memoryos/__init__.py
memoryos/long_term.py
memoryos/memoryos.py
memoryos/mid_term.py
memoryos/prompts.py
memoryos/retriever.py
memoryos/short_term.py
memoryos/updater.py
memoryos/utils.py
memoryos_bailab-0.1.0.dist-info/METADATA
memoryos_bailab-0.1.0.dist-info/WHEEL
memoryos_bailab-0.1.0.dist-info/top_level.txt
memoryos_bailab-0.1.0.dist-info/RECORD
