Metadata-Version: 2.4
Name: MemoryOS-BaiLab
Version: 0.1.0
Summary: 一个智能记忆管理系统，支持短期、中期和长期记忆存储与检索
Author: Jiazheng Kang
Author-email: 2457516191@qq.com
License: MIT
Keywords: memory,ai,llm,conversation,chatbot,openai
Classifier: Development Status :: 3 - Alpha
Classifier: Intended Audience :: Developers
Classifier: License :: OSI Approved :: MIT License
Classifier: Operating System :: OS Independent
Classifier: Programming Language :: Python :: 3
Classifier: Programming Language :: Python :: 3.8
Classifier: Programming Language :: Python :: 3.9
Classifier: Programming Language :: Python :: 3.10
Classifier: Programming Language :: Python :: 3.11
Classifier: Programming Language :: Python :: 3.12
Classifier: Topic :: Software Development :: Libraries :: Python Modules
Classifier: Topic :: Scientific/Engineering :: Artificial Intelligence
Requires-Python: >=3.8
Requires-Dist: openai
Requires-Dist: numpy
Requires-Dist: sentence-transformers
Requires-Dist: faiss-gpu
Requires-Dist: Flask
Requires-Dist: httpx[socks]
Dynamic: author
Dynamic: author-email
Dynamic: classifier
Dynamic: description
Dynamic: description-content-type
Dynamic: keywords
Dynamic: license
Dynamic: requires-dist
Dynamic: requires-python
Dynamic: summary
